pil_image_converter-3.0.3.dist-info/METADATA
pil_image_converter-3.0.3.dist-info/WHEEL
pil_image_converter-3.0.3.dist-info/entry_points.txt
pil_image_converter-3.0.3.dist-info/licenses/LICENSE
pil_image_converter/__init__.py
pil_image_converter/__main__.py
pil_image_converter/image_collector.py
pil_image_converter/image_converter.py
pil_image_converter-3.0.3.dist-info/RECORD
