Metadata-Version: 2.1
Name: pil_image_converter
Version: 3.0.3
Summary: Converts images from one format to another using Pillow. Currently supports JPG, PNG, BMP, and WebP.
Author-Email: Daethyra <109057945+Daethyra@users.noreply.github.com>
License: MIT
Requires-Python: <4.0,>=3.13
Requires-Dist: pillow<12.0.0,>=11.0.0
